{
  "month": "2026-06",
  "generated_at": "2026-06-03T08:00:07.577747+00:00",
  "meta": {
    "totals": {
      "spend": 988.11,
      "impressions": 144910,
      "clicks": 4389,
      "reach": 89221,
      "purchases": 52.0,
      "revenue": 2649.27,
      "ctr": 3.03,
      "cpc": 0.23,
      "cpm": 6.82,
      "cpa": 19.0,
      "roas": 2.68
    },
    "daily": [
      {
        "date": "2026-06-01",
        "spend": 443.29,
        "impressions": 67697,
        "clicks": 2090,
        "reach": 48632,
        "purchases": 30.0,
        "revenue": 1606.65,
        "ctr": 3.09,
        "cpc": 0.21,
        "cpm": 6.55,
        "cpa": 14.78,
        "roas": 3.62
      },
      {
        "date": "2026-06-02",
        "spend": 456.51,
        "impressions": 67118,
        "clicks": 1944,
        "reach": 48111,
        "purchases": 20.0,
        "revenue": 976.47,
        "ctr": 2.9,
        "cpc": 0.23,
        "cpm": 6.8,
        "cpa": 22.83,
        "roas": 2.14
      },
      {
        "date": "2026-06-03",
        "spend": 88.31,
        "impressions": 10095,
        "clicks": 355,
        "reach": 8246,
        "purchases": 2.0,
        "revenue": 66.15,
        "ctr": 3.52,
        "cpc": 0.25,
        "cpm": 8.75,
        "cpa": 44.16,
        "roas": 0.75
      }
    ],
    "campaigns": [
      {
        "campaign": "Electrolytes - Salty Lemon_Acquisition_Spain_Sales_Evergreen Campaign_2026-02-26",
        "spend": 482.12,
        "impressions": 56206,
        "clicks": 682,
        "reach": 24558,
        "purchases": 29.0,
        "revenue": 1575.68,
        "ctr": 1.21,
        "cpc": 0.71,
        "cpm": 8.58,
        "cpa": 16.62,
        "roas": 3.27
      },
      {
        "campaign": "Electrolytes - Salty Lemon_Acquisition_Spain_Sales_Press Campaign_2026-03-10",
        "spend": 505.57,
        "impressions": 88638,
        "clicks": 3704,
        "reach": 74761,
        "purchases": 23.0,
        "revenue": 1073.59,
        "ctr": 4.18,
        "cpc": 0.14,
        "cpm": 5.7,
        "cpa": 21.98,
        "roas": 2.12
      }
    ],
    "adsets": [
      {
        "campaign": "Electrolytes - Salty Lemon_Acquisition_Spain_Sales_Evergreen Campaign_2026-02-26",
        "adset": "Spain_Broad_Fatigue - Work_MFO_All ages_Auto bidding_All placements_2026-02-25",
        "spend": 166.13,
        "impressions": 18547,
        "clicks": 169,
        "reach": 10489,
        "purchases": 9.0,
        "revenue": 409.04,
        "ctr": 0.91,
        "cpc": 0.98,
        "cpm": 8.96,
        "cpa": 18.46,
        "roas": 2.46
      },
      {
        "campaign": "Electrolytes - Salty Lemon_Acquisition_Spain_Sales_Evergreen Campaign_2026-02-26",
        "adset": "Spain_Broad_Fatigue - Running_MFO_All ages_Auto bidding_All placements_2026-02-25",
        "spend": 158.01,
        "impressions": 21353,
        "clicks": 243,
        "reach": 12847,
        "purchases": 10.0,
        "revenue": 615.75,
        "ctr": 1.14,
        "cpc": 0.65,
        "cpm": 7.4,
        "cpa": 15.8,
        "roas": 3.9
      },
      {
        "campaign": "Electrolytes - Salty Lemon_Acquisition_Spain_Sales_Evergreen Campaign_2026-02-26",
        "adset": "Spain_Broad_Fatigue - General_MFO_All ages_Auto bidding_All placements_2026-02-25",
        "spend": 157.98,
        "impressions": 16306,
        "clicks": 270,
        "reach": 11098,
        "purchases": 10.0,
        "revenue": 550.89,
        "ctr": 1.66,
        "cpc": 0.59,
        "cpm": 9.69,
        "cpa": 15.8,
        "roas": 3.49
      },
      {
        "campaign": "Electrolytes - Salty Lemon_Acquisition_Spain_Sales_Press Campaign_2026-03-10",
        "adset": "Spain_Broad_Press-ElMundo_MFO_All ages_Auto bidding_All placements_2026-03-10",
        "spend": 362.99,
        "impressions": 67585,
        "clicks": 3212,
        "reach": 63823,
        "purchases": 15.0,
        "revenue": 818.44,
        "ctr": 4.75,
        "cpc": 0.11,
        "cpm": 5.37,
        "cpa": 24.2,
        "roas": 2.25
      },
      {
        "campaign": "Electrolytes - Salty Lemon_Acquisition_Spain_Sales_Press Campaign_2026-03-10",
        "adset": "Spain_Broad_Press-Men'sHealth_MFO_All ages_Auto bidding_All placements_2026-04-21",
        "spend": 68.34,
        "impressions": 11610,
        "clicks": 368,
        "reach": 9928,
        "purchases": 5.0,
        "revenue": 160.65,
        "ctr": 3.17,
        "cpc": 0.19,
        "cpm": 5.89,
        "cpa": 13.67,
        "roas": 2.35
      },
      {
        "campaign": "Electrolytes - Salty Lemon_Acquisition_Spain_Sales_Press Campaign_2026-03-10",
        "adset": "Spain_Broad_Press-OkDiario_MFO_All ages_Auto bidding_All placements_2026-05-21",
        "spend": 74.65,
        "impressions": 9502,
        "clicks": 127,
        "reach": 5831,
        "purchases": 3.0,
        "revenue": 94.5,
        "ctr": 1.34,
        "cpc": 0.59,
        "cpm": 7.86,
        "cpa": 24.88,
        "roas": 1.27
      }
    ],
    "platforms": [
      {
        "platform": "audience_network",
        "spend": 1.54,
        "impressions": 652,
        "clicks": 50,
        "reach": 105,
        "purchases": 3.0,
        "revenue": 66.15,
        "ctr": 7.67,
        "cpc": 0.03,
        "cpm": 2.37,
        "cpa": 0.51,
        "roas": 42.82
      },
      {
        "platform": "facebook",
        "spend": 116.03,
        "impressions": 25968,
        "clicks": 765,
        "reach": 15315,
        "purchases": 10.0,
        "revenue": 565.1,
        "ctr": 2.95,
        "cpc": 0.15,
        "cpm": 4.47,
        "cpa": 11.6,
        "roas": 4.87
      },
      {
        "platform": "instagram",
        "spend": 869.49,
        "impressions": 118152,
        "clicks": 3570,
        "reach": 75503,
        "purchases": 39.0,
        "revenue": 2018.02,
        "ctr": 3.02,
        "cpc": 0.24,
        "cpm": 7.36,
        "cpa": 22.29,
        "roas": 2.32
      },
      {
        "platform": "messenger",
        "spend": 0.0,
        "impressions": 1,
        "clicks": 0,
        "reach": 1,
        "purchases": 0.0,
        "revenue": 0.0,
        "ctr": 0.0,
        "cpc": 0.0,
        "cpm": 0.0,
        "cpa": 0.0,
        "roas": 0.0
      },
      {
        "platform": "threads",
        "spend": 0.32,
        "impressions": 135,
        "clicks": 4,
        "reach": 128,
        "purchases": 0.0,
        "revenue": 0.0,
        "ctr": 2.96,
        "cpc": 0.08,
        "cpm": 2.38,
        "cpa": 0.0,
        "roas": 0.0
      },
      {
        "platform": "unknown",
        "spend": 0.03,
        "impressions": 3,
        "clicks": 0,
        "reach": 3,
        "purchases": 0.0,
        "revenue": 0.0,
        "ctr": 0.0,
        "cpc": 0.0,
        "cpm": 10.03,
        "cpa": 0.0,
        "roas": 0.0
      }
    ],
    "creatives": [
      {
        "creative_id": "3937899833178389",
        "ad_name": "id.2026-03-10-Creative El Mundo_format.Image_product.Electrolytes - Salty Lemon_persona.Trend Follower_angle.Emotional Benefit - Therapeutic Value_style.Product - Lifestyle_copy.C1_type.New - Performance_promo.No promo_url.Landing page_vidlength.none_creator._hook.Vuelve al Ruedo_creativeCTA.Learn More / Discover",
        "thumbnail_url": "https://scontent-hel3-1.xx.fbcdn.net/v/t45.1600-4/649506859_941401722172525_1703411262447133523_n.png?_nc_cat=102&ccb=1-7&_nc_ohc=0q2tLW2LLSsQ7kNvwEEjgtc&_nc_oc=AdoneinAkjQVmOQM6OONBarUKEJzi_eV-BSKakIMLLXZUb6mSnuSbmMd6ACi9bBzFoO1ATODb0rkTC6ASNRfKCSL&_nc_zt=1&_nc_ht=scontent-hel3-1.xx&edm=AAwGEdEEAAAA&_nc_gid=k1A-hEBnBcoo-n6E_HSTSg&_nc_tpa=Q5bMBQEGJUcI1w8J_0bbWEBPcJcicCsqfdB6xG9eELMGiILOIt2Hl7AIva-btHlSllO7Wl5ssUmNR2aO&stp=c0.5000x0.5000f_dst-emg0_p64x64_q75_tt6&ur=52f3c4&_nc_sid=58080a&oh=00_Af_Qg_fJEAk-dKUPwtuHG-wRAiuSDJpmTjBTukpC_EaaQQ&oe=6A25AF6F",
        "title": null,
        "body": null,
        "campaigns": [
          "Electrolytes - Salty Lemon_Acquisition_Spain_Sales_Press Campaign_2026-03-10"
        ],
        "adsets": [
          "Spain_Broad_Press-ElMundo_MFO_All ages_Auto bidding_All placements_2026-03-10"
        ],
        "spend": 362.99,
        "impressions": 67585,
        "clicks": 3212,
        "reach": 63823,
        "purchases": 15.0,
        "revenue": 818.44,
        "ctr": 4.75,
        "cpc": 0.11,
        "cpa": 24.2,
        "roas": 2.25
      },
      {
        "creative_id": "1205576198031279",
        "ad_name": "id.2026-02-12-Creative 39_format.Video_product.Electrolytes - Salty Lemon_persona.Trend Follower_angle.Emotional Benefit - Therapeutic Value_style.Product - UGC_copy.C1_type.New - Performance_promo.No promo_url.Landing page_vidlength.15-30s_creator.IA_hook._creativeCTA.Learn More / Discover",
        "thumbnail_url": "https://scontent-hel3-1.xx.fbcdn.net/v/t15.5256-10/628534979_1240931637470298_8896003931047812488_n.jpg?_nc_cat=111&ccb=1-7&_nc_ohc=xW4H_fAHW3EQ7kNvwGsaQpj&_nc_oc=Adq2_A3BEhV4iqrMgEJcXdg7YtPzUEr7z9bmfP7q_0xBOuNlHDPUjbnguWwQyv7q7_kR-zCHqCqsVNAFnXdg9hic&_nc_zt=23&_nc_ht=scontent-hel3-1.xx&edm=AAwGEdEEAAAA&_nc_gid=k1A-hEBnBcoo-n6E_HSTSg&_nc_tpa=Q5bMBQFVPrPg67iLXNS3D-lz7MV-hm5K02x73BhE3TirTSRAtOYFRjQ4wUcdl93ZKXdylGea2g0hlsnb&stp=c0.5000x0.5000f_dst-emg0_p64x64_q75_tt6&ur=5fad0e&_nc_sid=58080a&oh=00_Af_gld_SqEJZQJc8julVerWCUcj4-b1-PPMAzJo5zJHvXA&oe=6A25ABA7",
        "title": "Cánsate menos, rinde mejor",
        "body": "¿Te notas cansado sin motivo claro?\n\nLa deshidratación no siempre se siente como sed.\nA veces aparece como fatiga, apatía, bajo rendimiento.\n\nMantén tu equilibrio mineral y siente la diferencia.\n\nLIT. Simple. Funcional. Sin azúcar.",
        "campaigns": [
          "Electrolytes - Salty Lemon_Acquisition_Spain_Sales_Evergreen Campaign_2026-02-26"
        ],
        "adsets": [
          "Spain_Broad_Fatigue - General_MFO_All ages_Auto bidding_All placements_2026-02-25"
        ],
        "spend": 151.91,
        "impressions": 15781,
        "clicks": 263,
        "reach": 10990,
        "purchases": 9.0,
        "revenue": 482.96,
        "ctr": 1.67,
        "cpc": 0.58,
        "cpa": 16.88,
        "roas": 3.18
      },
      {
        "creative_id": "959238816621510",
        "ad_name": "id.2026-03-11-Creative2-Marzo_format.Image_product.Electrolytes - Salty Lemon_persona.High-Performer_angle.Emotional Benefit - Therapeutic Value_style.Product - Lifestyle_copy.C2_type.New - Performance_promo.No promo_url.Landing page_vidlength.none_creator._hook.Vuelve al Ruedo - Running_creativeCTA.Learn More / Discover",
        "thumbnail_url": "https://scontent-hel3-1.xx.fbcdn.net/v/t45.1600-4/649948057_941416465504384_4264710786611160246_n.png?_nc_cat=101&ccb=1-7&_nc_ohc=7oJ35Eh8M_wQ7kNvwELzpTu&_nc_oc=AdoTjIwlCBz1QDoxzeeB0y6-qQxQmNGCmjsboUA11T8ESHkoC10tm059K9hnrY6hVC-aiEMFRqnOjvwodhf1TZ3I&_nc_zt=1&_nc_ht=scontent-hel3-1.xx&edm=AAwGEdEEAAAA&_nc_gid=k1A-hEBnBcoo-n6E_HSTSg&_nc_tpa=Q5bMBQEnr537c3PWGxIg8dFUDqmcgmrCqjRXKvST1ZzLnCrDVZ-zatNlv30Ajf5XITCVfpU7u-Z9KYKX&stp=c0.5000x0.5000f_dst-emg0_p64x64_q75_tt6&ur=52f3c4&_nc_sid=58080a&oh=00_Af9UAeq-QM4JoUyFwpEX6EyoCDtPMCaQdjxbv3ZGVS9U9Q&oe=6A25B8C7",
        "title": null,
        "body": null,
        "campaigns": [
          "Electrolytes - Salty Lemon_Acquisition_Spain_Sales_Evergreen Campaign_2026-02-26"
        ],
        "adsets": [
          "Spain_Broad_Fatigue - Work_MFO_All ages_Auto bidding_All placements_2026-02-25"
        ],
        "spend": 132.16,
        "impressions": 14567,
        "clicks": 132,
        "reach": 9506,
        "purchases": 6.0,
        "revenue": 314.54,
        "ctr": 0.91,
        "cpc": 1.0,
        "cpa": 22.03,
        "roas": 2.38
      },
      {
        "creative_id": "1434260378443660",
        "ad_name": "id.2026-03-11-Creative8-Marzo_format.Image_product.Electrolytes - Salty Lemon_persona.High-Performer_angle.Emotional Benefit - Therapeutic Value_style.Product - Lifestyle_copy.C2_type.New - Performance_promo.No promo_url.Landing page_vidlength.none_creator._hook.Vuelve al Ruedo - Running_creativeCTA.Learn More / Discover",
        "thumbnail_url": "https://scontent-hel3-1.xx.fbcdn.net/v/t45.1600-4/647179898_941416562171041_3694500736531613878_n.png?_nc_cat=108&ccb=1-7&_nc_ohc=ZCUrTq9o0r0Q7kNvwGmQmIo&_nc_oc=AdqOwX7JBDNebJ2AokFTZIPzHqe3LF-MwUQjN-jNoo8zMlMQVurgnFH6zA0OfhCZtpPh8BW4POIkfOk550UmUM9N&_nc_zt=1&_nc_ht=scontent-hel3-1.xx&edm=AAwGEdEEAAAA&_nc_gid=k1A-hEBnBcoo-n6E_HSTSg&_nc_tpa=Q5bMBQGXd-JUZyV3T3fVOPDUDoQYx4m8Y3w1c8pgMS3_hPWN_7bXrldh4eiIXNDoF-cYyLWQylYQqKn6&stp=c0.5000x0.5000f_dst-emg0_p64x64_q75_tt6&ur=52f3c4&_nc_sid=58080a&oh=00_Af-2YjxRnK6VV9siLpLgIDHLQyXx8VtJ5ochGCVvfZSoZg&oe=6A25B45E",
        "title": null,
        "body": null,
        "campaigns": [
          "Electrolytes - Salty Lemon_Acquisition_Spain_Sales_Evergreen Campaign_2026-02-26"
        ],
        "adsets": [
          "Spain_Broad_Fatigue - Running_MFO_All ages_Auto bidding_All placements_2026-02-25"
        ],
        "spend": 130.39,
        "impressions": 17914,
        "clicks": 204,
        "reach": 11870,
        "purchases": 7.0,
        "revenue": 198.45,
        "ctr": 1.14,
        "cpc": 0.64,
        "cpa": 18.63,
        "roas": 1.52
      },
      {
        "creative_id": "823531750785268",
        "ad_name": "id.2026-05-21-Creative OkDiario_format.Image_product.Electrolytes - Salty Lemon_persona.Trend Follower_angle.Emotional Benefit - Therapeutic Value_style.Product - Lifestyle_copy.C1_type.New - Performance_promo.No promo_url.Landing page_vidlength.none_creator._hook.Vuelve al Ruedo_creativeCTA.Learn More / Discover",
        "thumbnail_url": "https://scontent-hel3-1.xx.fbcdn.net/v/t45.1600-4/703563889_1001247906187906_6174079529367902367_n.png?_nc_cat=100&ccb=1-7&_nc_ohc=Iwg8uk0QKy0Q7kNvwFf34Zm&_nc_oc=AdpTnFIIbfl3TzqLKpsLxPXmDti_nIQSXfdyifN6OfLJ6OWQlBTuPwflwwtsnjdWL45-XPYqJ9g0Ksb5MV6sN81c&_nc_zt=1&_nc_ht=scontent-hel3-1.xx&edm=AAwGEdEEAAAA&_nc_gid=k1A-hEBnBcoo-n6E_HSTSg&_nc_tpa=Q5bMBQHy64hnIKBrh_Z8XLS7RpklmWBVfnKpejsotwhOjhVn3A3_VjOddJY-swFiGb2vwURV9XmPj3bc&stp=c0.5000x0.5000f_dst-emg0_p64x64_q75_tt6&ur=52f3c4&_nc_sid=58080a&oh=00_Af-tfr2wjVbAfmp1CheGTVPpCQWkemnSs_jZZTCQFCAk-w&oe=6A25A86A",
        "title": null,
        "body": null,
        "campaigns": [
          "Electrolytes - Salty Lemon_Acquisition_Spain_Sales_Press Campaign_2026-03-10"
        ],
        "adsets": [
          "Spain_Broad_Press-OkDiario_MFO_All ages_Auto bidding_All placements_2026-05-21"
        ],
        "spend": 74.65,
        "impressions": 9502,
        "clicks": 127,
        "reach": 5831,
        "purchases": 3.0,
        "revenue": 94.5,
        "ctr": 1.34,
        "cpc": 0.59,
        "cpa": 24.88,
        "roas": 1.27
      },
      {
        "creative_id": "1610011106973858",
        "ad_name": "id.2026-04-01-Creative Men's Health_format.Image_product.Electrolytes - Salty Lemon_persona.Trend Follower_angle.Emotional Benefit - Therapeutic Value_style.Product - Lifestyle_copy.C1_type.New - Performance_promo.No promo_url.Landing page_vidlength.none_creator._hook.Vuelve al Ruedo_creativeCTA.Learn More / Discover",
        "thumbnail_url": "https://scontent-hel3-1.xx.fbcdn.net/v/t45.1600-4/657356925_952966991015998_8195544919979397495_n.png?_nc_cat=101&ccb=1-7&_nc_ohc=YNB-szAsb24Q7kNvwHL1H7z&_nc_oc=AdrtdB6KI9EJPSWBDQITdqqRMoissNcnBwB2hVbIez5N7aMsULoj-MJmSUnZCG3tltpO4U4fJKEJ9AWoPTjOH_pF&_nc_zt=1&_nc_ht=scontent-hel3-1.xx&edm=AAwGEdEEAAAA&_nc_gid=k1A-hEBnBcoo-n6E_HSTSg&_nc_tpa=Q5bMBQHbrje2PMEXG77koMntq5t4BWOIHgGGr6vsSyuZgPfbsZs46mUCBA5I3mbvuymNXPkqgJuXO6JN&stp=c0.5000x0.5000f_dst-emg0_p64x64_q75_tt6&ur=52f3c4&_nc_sid=58080a&oh=00_Af8VtDgZRnkAXyRHJiXdjxiSnQ8qfKvfgwOYx0-6_NDUOw&oe=6A25A4F1",
        "title": null,
        "body": null,
        "campaigns": [
          "Electrolytes - Salty Lemon_Acquisition_Spain_Sales_Press Campaign_2026-03-10"
        ],
        "adsets": [
          "Spain_Broad_Press-Men'sHealth_MFO_All ages_Auto bidding_All placements_2026-04-21"
        ],
        "spend": 68.35,
        "impressions": 11618,
        "clicks": 368,
        "reach": 9928,
        "purchases": 5.0,
        "revenue": 160.65,
        "ctr": 3.17,
        "cpc": 0.19,
        "cpa": 13.67,
        "roas": 2.35
      },
      {
        "creative_id": "4341980809394940",
        "ad_name": "id.2026-03-11-Creative4-Marzo_format.Image_product.Electrolytes - Salty Lemon_persona.High-Performer_angle.Emotional Benefit - Therapeutic Value_style.Product - Lifestyle_copy.C2_type.New - Performance_promo.No promo_url.Landing page_vidlength.none_creator._hook.Vuelve al Ruedo - Running_creativeCTA.Learn More / Discover",
        "thumbnail_url": "https://scontent-hel3-1.xx.fbcdn.net/v/t45.1600-4/649507475_941416448837719_5098115077455737024_n.png?_nc_cat=108&ccb=1-7&_nc_ohc=C_Jq8rmiKhQQ7kNvwEcKDmg&_nc_oc=AdruL2kTiqiMDy3MkF2bGHux06cPiP98PwBDQxro_exTgFTR0fXC2mxvDGAbU25UaFmQ4o7vuNTkpAIHC_J7FmsP&_nc_zt=1&_nc_ht=scontent-hel3-1.xx&edm=AAwGEdEEAAAA&_nc_gid=k1A-hEBnBcoo-n6E_HSTSg&_nc_tpa=Q5bMBQF8T_37lmn_uJywx-fRnH3y1JsIdBdJIOrAPEVueI65snmaW7xoFT6lJRtn4D2V3YzLjkBJuUWK&stp=c0.5000x0.5000f_dst-emg0_p64x64_q75_tt6&ur=52f3c4&_nc_sid=58080a&oh=00_Af89wZB2SjlUoRJZbhelnkZN6weI674_aOfxTMTeZa2v_w&oe=6A25BA85",
        "title": null,
        "body": null,
        "campaigns": [
          "Electrolytes - Salty Lemon_Acquisition_Spain_Sales_Evergreen Campaign_2026-02-26"
        ],
        "adsets": [
          "Spain_Broad_Fatigue - Work_MFO_All ages_Auto bidding_All placements_2026-02-25"
        ],
        "spend": 33.97,
        "impressions": 3980,
        "clicks": 37,
        "reach": 2552,
        "purchases": 3.0,
        "revenue": 94.5,
        "ctr": 0.93,
        "cpc": 0.92,
        "cpa": 11.32,
        "roas": 2.78
      },
      {
        "creative_id": "1202730495274217",
        "ad_name": "id.2026-03-11-Creative5-Marzo_format.Image_product.Electrolytes - Salty Lemon_persona.High-Performer_angle.Emotional Benefit - Therapeutic Value_style.Product - Lifestyle_copy.C2_type.New - Performance_promo.No promo_url.Landing page_vidlength.none_creator._hook.Vuelve al Ruedo - Running_creativeCTA.Learn More / Discover",
        "thumbnail_url": "https://scontent-hel3-1.xx.fbcdn.net/v/t45.1600-4/651448867_942100395435991_7224662586750171527_n.png?_nc_cat=108&ccb=1-7&_nc_ohc=vkRzpa1VeKEQ7kNvwFLgIbg&_nc_oc=Adp4g5UnOrAnwGg58_5QUARp0HgHg9pcXMOQFLq1lQf2LFOYCAdxtNyyzGgW8W3uT2OMecN_t0YET6t3xa0NhZ5b&_nc_zt=1&_nc_ht=scontent-hel3-1.xx&edm=AAwGEdEEAAAA&_nc_gid=k1A-hEBnBcoo-n6E_HSTSg&_nc_tpa=Q5bMBQGpL7pTILvCipFpO5m_JvKKb7m-rySCSMj9WtG9yeV1LFVS_65gvOh1YXZ48o95JW8lk-S-qMUG&stp=c0.5000x0.5000f_dst-emg0_p64x64_q75_tt6&ur=52f3c4&_nc_sid=58080a&oh=00_Af8QlZxKky4LcI9CX74K0TIgNdqrnbTHGCXZ61WOqex8LA&oe=6A25BD74",
        "title": null,
        "body": null,
        "campaigns": [
          "Electrolytes - Salty Lemon_Acquisition_Spain_Sales_Evergreen Campaign_2026-02-26"
        ],
        "adsets": [
          "Spain_Broad_Fatigue - Running_MFO_All ages_Auto bidding_All placements_2026-02-25"
        ],
        "spend": 13.89,
        "impressions": 1612,
        "clicks": 16,
        "reach": 1275,
        "purchases": 1.0,
        "revenue": 37.8,
        "ctr": 0.99,
        "cpc": 0.87,
        "cpa": 13.89,
        "roas": 2.72
      },
      {
        "creative_id": "1244941077833948",
        "ad_name": "id.2026-03-11-UGC Guava_format.Video_product.Electrolytes - Salty Lemon_persona.Trend Follower_angle.Emotional Benefit - Therapeutic Value_style.Product - UGC_copy.C1_type.New - Performance_promo.No promo_url.Landing page_vidlength.15-30s_creator.IA_hook._creativeCTA.Learn More / Discover",
        "thumbnail_url": "https://scontent-hel3-1.xx.fbcdn.net/v/t15.5256-10/649527904_1431724478444285_5912203667980242891_n.jpg?_nc_cat=106&ccb=1-7&_nc_ohc=VFnejXqSG6MQ7kNvwEixYyx&_nc_oc=Adq6oSMv85FnljPOM_sK_2TI4nDk2yL1FAHmFcViJjGUqf4sp6E_11pOiLxQJePhc35fwZZXDnSL9fTfevuB4Z22&_nc_zt=23&_nc_ht=scontent-hel3-1.xx&edm=AAwGEdEEAAAA&_nc_gid=k1A-hEBnBcoo-n6E_HSTSg&_nc_tpa=Q5bMBQFNjTgDAvfFU3Hrcya0mmXtAeikpxZEsKIWOxgkkA1rL9s_yQ36j-MjMTmm7_t-Hov_rwZU8XLl&stp=c0.5000x0.5000f_dst-emg0_p64x64_q75_tt6&ur=5fad0e&_nc_sid=58080a&oh=00_Af-SkkOwQgeoiv4xGYNDKt4ocSF-F9IAr5CUQUKBHnO3gA&oe=6A259CBA",
        "title": "Más foco. Menos bajón.",
        "body": "Reuniones, llamadas, pantalla… y cero energía.\nNo todo es falta de café.\n\nSi sudas, si te mueves, si vives activo, necesitas reponer minerales.\n\nLIT te ayuda a mantener claridad y estabilidad durante el día.",
        "campaigns": [
          "Electrolytes - Salty Lemon_Acquisition_Spain_Sales_Evergreen Campaign_2026-02-26"
        ],
        "adsets": [
          "Spain_Broad_Fatigue - Running_MFO_All ages_Auto bidding_All placements_2026-02-25"
        ],
        "spend": 11.25,
        "impressions": 1570,
        "clicks": 20,
        "reach": 1264,
        "purchases": 2.0,
        "revenue": 379.5,
        "ctr": 1.27,
        "cpc": 0.56,
        "cpa": 5.62,
        "roas": 33.73
      },
      {
        "creative_id": "26676184238633236",
        "ad_name": "id.2025-10-27-UGC Chica Rojo_format.Video_product.Electrolytes - Salty Lemon_persona.Wellness Enthusiast_angle.Emotional Benefit - Wellness_style.People - Lifestyle_copy.C1_type.New - Performance_promo.No promo_url.Landing page_vidlength.15-30s_creator.Manon_hook.Cansancio_creativeCTA.Shop Now Prompt",
        "thumbnail_url": "https://scontent-hel3-1.xx.fbcdn.net/v/t15.5256-10/566559291_1523134622241221_5289066096830835121_n.jpg?_nc_cat=109&ccb=1-7&_nc_ohc=ny0f3U1uodEQ7kNvwFL4010&_nc_oc=Adq_iweLYvlVN8KYUPbv6oSHqyAnb6sOxoccSiUanhA0-3IMBTm-Fhg2skEyl6F4K51mO6EKOFJoZvfZJwY_jPWu&_nc_zt=23&_nc_ht=scontent-hel3-1.xx&edm=AAwGEdEEAAAA&_nc_gid=k1A-hEBnBcoo-n6E_HSTSg&_nc_tpa=Q5bMBQGoMFmyTxKh8pLw4p1eNagHEkGY4y0nzOxKHH_m6CvY3sT_hN5L6e_VvbOmVVv_MH3NqJ-IMRyc&stp=c0.5000x0.5000f_dst-emg0_p64x64_q75_tt6&ur=5fad0e&_nc_sid=58080a&oh=00_Af-ZOpXXyYTIPazvT5RN2kiS4fTYeyvEx764vLv53H_Z6w&oe=6A25C15D",
        "title": "Cánsate menos, rinde mejor",
        "body": "¿Te notas cansado sin motivo claro?\n\nLa deshidratación no siempre se siente como sed.\nA veces aparece como fatiga, apatía, bajo rendimiento.\n\nMantén tu equilibrio mineral y siente la diferencia.\n\nLIT. Simple. Funcional. Sin azúcar.",
        "campaigns": [
          "Electrolytes - Salty Lemon_Acquisition_Spain_Sales_Evergreen Campaign_2026-02-26"
        ],
        "adsets": [
          "Spain_Broad_Fatigue - General_MFO_All ages_Auto bidding_All placements_2026-02-25"
        ],
        "spend": 4.64,
        "impressions": 332,
        "clicks": 5,
        "reach": 295,
        "purchases": 1.0,
        "revenue": 67.93,
        "ctr": 1.51,
        "cpc": 0.93,
        "cpa": 4.64,
        "roas": 14.64
      },
      {
        "creative_id": "2389018354875395",
        "ad_name": "id.2026-03-11-Creative7-Marzo_format.Image_product.Electrolytes - Salty Lemon_persona.High-Performer_angle.Emotional Benefit - Therapeutic Value_style.Product - Lifestyle_copy.C2_type.New - Performance_promo.No promo_url.Landing page_vidlength.none_creator._hook.Vuelve al Ruedo - Running_creativeCTA.Learn More / Discover",
        "thumbnail_url": "https://scontent-hel3-1.xx.fbcdn.net/v/t45.1600-4/647435580_941416532171044_7940677406777282763_n.png?_nc_cat=107&ccb=1-7&_nc_ohc=RsVgqYDlA9oQ7kNvwEWM0Ss&_nc_oc=Adr0KmtHlKNaY5KtBJyYim9KDtq1eRWJxz6_5dO-bMYwvzrRF3TfAkwDdcixzxCKL3XcIrTB8cAGdmJlw2Cy9IGH&_nc_zt=1&_nc_ht=scontent-hel3-1.xx&edm=AAwGEdEEAAAA&_nc_gid=k1A-hEBnBcoo-n6E_HSTSg&_nc_tpa=Q5bMBQGD92qynL948xKzMCJUSkQ3U3CuVjiPY42Eg5Z0iEGy9si_eKGs7gYLMPexSHFZxgfxYyrOBep5&stp=c0.5000x0.5000f_dst-emg0_p64x64_q75_tt6&ur=52f3c4&_nc_sid=58080a&oh=00_Af_SYqrvNTsOLd6520ls22d2ohNZ6wW9NTBd2LdxquAdZg&oe=6A25B091",
        "title": null,
        "body": null,
        "campaigns": [
          "Electrolytes - Salty Lemon_Acquisition_Spain_Sales_Evergreen Campaign_2026-02-26"
        ],
        "adsets": [
          "Spain_Broad_Fatigue - Running_MFO_All ages_Auto bidding_All placements_2026-02-25"
        ],
        "spend": 1.59,
        "impressions": 158,
        "clicks": 1,
        "reach": 146,
        "purchases": 0.0,
        "revenue": 0.0,
        "ctr": 0.63,
        "cpc": 1.59,
        "cpa": 0.0,
        "roas": 0.0
      },
      {
        "creative_id": "4038611136385489",
        "ad_name": "id.2026-01-12-Creative 68_format.Image_product.Electrolytes - Salty Lemon_persona.Trend Follower_angle.Emotional Benefit - Therapeutic Value_style.Product - Lifestyle_copy.C1_type.New - Performance_promo.No promo_url.Landing page_vidlength.none_creator._hook.Vuelve al Ruedo_creativeCTA.Learn More / Discover",
        "thumbnail_url": "https://scontent-hel3-1.xx.fbcdn.net/v/t45.1600-4/634334553_919484281030936_5045441572585261392_n.png?_nc_cat=107&ccb=1-7&_nc_ohc=3JkpzLBPJ_UQ7kNvwGI_rh9&_nc_oc=Adr2cJjsimQSzDukiEaT1ekafGxooaXBJMV-ZGkv6ZWhrfKyQYMeALYhkTtuTy8KGk6wqdt3jP0uDyGfr2aK0fEw&_nc_zt=1&_nc_ht=scontent-hel3-1.xx&edm=AAwGEdEEAAAA&_nc_gid=k1A-hEBnBcoo-n6E_HSTSg&_nc_tpa=Q5bMBQEcV6DxZtV0p92nfjgP2LtJPet83v8fHqIk6eZxge0IimTjJc-vaRN6BItstqtHKB6YLmbhRL31&stp=c0.5000x0.5000f_dst-emg0_p64x64_q75_tt6&ur=52f3c4&_nc_sid=58080a&oh=00_Af_wPUBCmOv5jPZq371JjsHZ7x7ydE3ckNps-ui3gM7ofA&oe=6A25C9DE",
        "title": null,
        "body": null,
        "campaigns": [
          "Electrolytes - Salty Lemon_Acquisition_Spain_Sales_Evergreen Campaign_2026-02-26"
        ],
        "adsets": [
          "Spain_Broad_Fatigue - General_MFO_All ages_Auto bidding_All placements_2026-02-25"
        ],
        "spend": 1.15,
        "impressions": 182,
        "clicks": 2,
        "reach": 173,
        "purchases": 0.0,
        "revenue": 0.0,
        "ctr": 1.1,
        "cpc": 0.57,
        "cpa": 0.0,
        "roas": 0.0
      },
      {
        "creative_id": "921810977159693",
        "ad_name": "id.2026-03-11-Creative6-Marzo_format.Image_product.Electrolytes - Salty Lemon_persona.High-Performer_angle.Emotional Benefit - Therapeutic Value_style.Product - Lifestyle_copy.C2_type.New - Performance_promo.No promo_url.Landing page_vidlength.none_creator._hook.Vuelve al Ruedo - Running_creativeCTA.Learn More / Discover",
        "thumbnail_url": "https://scontent-hel3-1.xx.fbcdn.net/v/t45.1600-4/649389296_941416375504393_6362389934218678432_n.png?_nc_cat=105&ccb=1-7&_nc_ohc=TSEq0pqUc-YQ7kNvwFmYAYV&_nc_oc=AdrLSyXh7yQyoqVjf9INrGIier9ZVqGVguVoOZBPiGpMX72DavnYwNGhMOwClJCuutLEtZIm2w5PsYH_7LtEFhqc&_nc_zt=1&_nc_ht=scontent-hel3-1.xx&edm=AAwGEdEEAAAA&_nc_gid=k1A-hEBnBcoo-n6E_HSTSg&_nc_tpa=Q5bMBQHE8cofDR9zYcHUBEnatcbtduUGdLi6zDql8N2hFLt_pEFXWaWos7j7iUuUaiW4JKqcvtqfu8uA&stp=c0.5000x0.5000f_dst-emg0_p64x64_q75_tt6&ur=52f3c4&_nc_sid=58080a&oh=00_Af9wkpWl4V3ik3-ZcRG-2czsxMbhEq7XuTcDG1z-lo_n_g&oe=6A25C8B7",
        "title": null,
        "body": null,
        "campaigns": [
          "Electrolytes - Salty Lemon_Acquisition_Spain_Sales_Evergreen Campaign_2026-02-26"
        ],
        "adsets": [
          "Spain_Broad_Fatigue - Running_MFO_All ages_Auto bidding_All placements_2026-02-25"
        ],
        "spend": 0.89,
        "impressions": 99,
        "clicks": 2,
        "reach": 88,
        "purchases": 0.0,
        "revenue": 0.0,
        "ctr": 2.02,
        "cpc": 0.45,
        "cpa": 0.0,
        "roas": 0.0
      },
      {
        "creative_id": "958354360012967",
        "ad_name": "id.2025-12-29-Creative 73_format.Video_product.Electrolytes - Salty Lemon_persona.Wellness Enthusiast_angle.Emotional Benefit - Wellness_style.People - Lifestyle_copy.C1_type.New - Performance_promo.No promo_url.Landing page_vidlength.15-30s_creator.Manon_hook.Cansancio_creativeCTA.Shop Now Prompt",
        "thumbnail_url": "https://scontent-hel3-1.xx.fbcdn.net/v/t15.5256-10/607341905_1541160537572856_8552563035764202750_n.jpg?_nc_cat=103&ccb=1-7&_nc_ohc=l4w3atzC6z8Q7kNvwEhQAPR&_nc_oc=AdqFT175PG7ORRaDK7u-eyD6fR5U0T02hjuApQgcrf_4ub7-98m7tD7Jd4ycrg2McP-eljm7VFnYG27NfLQWe_T2&_nc_zt=23&_nc_ht=scontent-hel3-1.xx&edm=AAwGEdEEAAAA&_nc_gid=k1A-hEBnBcoo-n6E_HSTSg&_nc_tpa=Q5bMBQHprd1KuXBnhY9wOHKS960zEYZbZtrN97zkVSSZ8VtnOPM-RZF6F7Hd9pudrRM2E6pPRNR0ZQds&stp=c0.5000x0.5000f_dst-emg0_p64x64_q75_tt6&ur=b696e2&_nc_sid=58080a&oh=00_Af8RYV8Vov9mKx3yCaaz2Cb5-Put9pZyw-xB2KV2FXceIw&oe=6A25B6DE",
        "title": null,
        "body": null,
        "campaigns": [
          "Electrolytes - Salty Lemon_Acquisition_Spain_Sales_Evergreen Campaign_2026-02-26"
        ],
        "adsets": [
          "Spain_Broad_Fatigue - General_MFO_All ages_Auto bidding_All placements_2026-02-25"
        ],
        "spend": 0.28,
        "impressions": 11,
        "clicks": 0,
        "reach": 11,
        "purchases": 0.0,
        "revenue": 0.0,
        "ctr": 0.0,
        "cpc": 0.0,
        "cpa": 0.0,
        "roas": 0.0
      }
    ]
  },
  "google": {
    "totals": {},
    "daily": [],
    "campaigns": [],
    "keywords": [],
    "gender": [],
    "age": []
  },
  "klaviyo": {
    "totals": {
      "revenue_total": 199.11,
      "revenue_campaigns": 0.0,
      "revenue_flows": 199.11,
      "sends": 355,
      "opens": 189,
      "clicks": 6,
      "unsubs": 3,
      "open_rate": 53.24,
      "click_rate": 1.69,
      "unsub_rate": 0.85
    },
    "daily": [
      {
        "date": "2026-06-01",
        "revenue": 0.0,
        "sends": 0,
        "opens": 0,
        "open_rate": 0.0
      },
      {
        "date": "2026-06-02",
        "revenue": 0.0,
        "sends": 0,
        "opens": 0,
        "open_rate": 0.0
      },
      {
        "date": "2026-06-03",
        "revenue": 0.0,
        "sends": 0,
        "opens": 0,
        "open_rate": 0.0
      }
    ],
    "flows": [
      {
        "flow_id": "UkkQhv",
        "name": "LF - Welcome",
        "status": "live",
        "sends": 82,
        "opens": 37,
        "clicks": 3,
        "unsubs": 1,
        "revenue": 95.16,
        "open_rate": 45.12,
        "click_rate": 3.66,
        "unsub_rate": 1.22
      },
      {
        "flow_id": "VzwdgK",
        "name": "Checkout Abandonado",
        "status": "live",
        "sends": 34,
        "opens": 16,
        "clicks": 1,
        "unsubs": 1,
        "revenue": 66.15,
        "open_rate": 47.06,
        "click_rate": 2.94,
        "unsub_rate": 2.94
      },
      {
        "flow_id": "URwaNT",
        "name": "Abandono de navegación - PP",
        "status": "live",
        "sends": 17,
        "opens": 9,
        "clicks": 1,
        "unsubs": 0,
        "revenue": 37.8,
        "open_rate": 52.94,
        "click_rate": 5.88,
        "unsub_rate": 0.0
      },
      {
        "flow_id": "UyQDRp",
        "name": "Order Experience Flow - Order #1",
        "status": "live",
        "sends": 194,
        "opens": 111,
        "clicks": 0,
        "unsubs": 1,
        "revenue": 0.0,
        "open_rate": 57.22,
        "click_rate": 0.0,
        "unsub_rate": 0.52
      },
      {
        "flow_id": "UAH3ug",
        "name": "Suscripción - Bienvenida",
        "status": "live",
        "sends": 13,
        "opens": 8,
        "clicks": 1,
        "unsubs": 0,
        "revenue": 0.0,
        "open_rate": 61.54,
        "click_rate": 7.69,
        "unsub_rate": 0.0
      },
      {
        "flow_id": "YnyQLZ",
        "name": "Abandono de navegación",
        "status": "live",
        "sends": 3,
        "opens": 1,
        "clicks": 0,
        "unsubs": 0,
        "revenue": 0.0,
        "open_rate": 33.33,
        "click_rate": 0.0,
        "unsub_rate": 0.0
      },
      {
        "flow_id": "QRkWPP",
        "name": "Suscripción - Cancelación",
        "status": "live",
        "sends": 12,
        "opens": 7,
        "clicks": 0,
        "unsubs": 0,
        "revenue": 0.0,
        "open_rate": 58.33,
        "click_rate": 0.0,
        "unsub_rate": 0.0
      }
    ],
    "campaigns": []
  },
  "shopify": {
    "totals": {
      "orders": 94,
      "revenue": 4699.95,
      "refunds": 0.0,
      "net_revenue": 4699.95,
      "aov": 50.0,
      "new_customers": 65,
      "returning_customers": 29,
      "subscription_orders": 60,
      "onetime_orders": 34,
      "subscription_revenue": 2691.38,
      "onetime_revenue": 2008.57,
      "subscription_pct": 63.83,
      "returning_pct": 30.85,
      "refund_rate": 0.0
    },
    "daily": [
      {
        "date": "2026-06-01",
        "orders": 49,
        "revenue": 2436.5,
        "refunds": 0.0,
        "aov": 49.72,
        "new": 30,
        "returning": 19,
        "subscription_orders": 30,
        "onetime_orders": 19
      },
      {
        "date": "2026-06-02",
        "orders": 39,
        "revenue": 2074.45,
        "refunds": 0.0,
        "aov": 53.19,
        "new": 29,
        "returning": 10,
        "subscription_orders": 27,
        "onetime_orders": 12
      },
      {
        "date": "2026-06-03",
        "orders": 4,
        "revenue": 132.3,
        "refunds": 0.0,
        "aov": 33.08,
        "new": 4,
        "returning": 0,
        "subscription_orders": 1,
        "onetime_orders": 3
      }
    ],
    "products": [
      {
        "product_id": "gid://shopify/Product/16008517550429",
        "title": "LIT Daily Hydration",
        "orders": 61,
        "units": 63,
        "revenue": 2735.97
      },
      {
        "product_id": "gid://shopify/Product/16182160523613",
        "title": "LIT Daily Hydration - Compra única",
        "orders": 30,
        "units": 40,
        "revenue": 1512.0
      },
      {
        "product_id": "gid://shopify/Product/16204004196701",
        "title": "LIT Box: Wholesale",
        "orders": 3,
        "units": 40,
        "revenue": 753.5
      }
    ],
    "breakdowns": {
      "new_vs_returning": [
        {
          "bucket": "new",
          "orders": 65
        },
        {
          "bucket": "returning",
          "orders": 29
        }
      ],
      "subscription_vs_onetime": [
        {
          "bucket": "subscription",
          "orders": 60,
          "revenue": 2691.38
        },
        {
          "bucket": "onetime",
          "orders": 34,
          "revenue": 2008.57
        }
      ]
    }
  },
  "wholesale": {
    "totals": {
      "orders": 92,
      "revenue": 4643.25,
      "paid": 4643.25,
      "pending": 0.0,
      "aov": 50.47,
      "paid_pct": 100.0,
      "accounts": 92
    },
    "daily": [
      {
        "date": "2026-06-01",
        "orders": 49,
        "revenue": 2436.5,
        "paid": 2436.5
      },
      {
        "date": "2026-06-02",
        "orders": 39,
        "revenue": 2074.45,
        "paid": 2074.45
      },
      {
        "date": "2026-06-03",
        "orders": 4,
        "revenue": 132.3,
        "paid": 132.3
      }
    ],
    "pipeline": [
      {
        "stage": "Prospects",
        "count": 11
      },
      {
        "stage": "Outreach / Visits",
        "count": 64
      },
      {
        "stage": "Qualified / In Communication",
        "count": 42
      },
      {
        "stage": "Lost",
        "count": 31
      },
      {
        "stage": "Order: Consignment",
        "count": 12
      }
    ],
    "top_accounts": [
      {
        "account": "Healthy Café Puerta de Alcalá",
        "orders": 1,
        "revenue": 280.5
      },
      {
        "account": "Candela Roure",
        "orders": 1,
        "revenue": 189.0
      },
      {
        "account": "KRONOSUPLEMENTS SL",
        "orders": 1,
        "revenue": 187.0
      },
      {
        "account": "Antonio Porteiro",
        "orders": 1,
        "revenue": 151.2
      },
      {
        "account": "SKYRSKYR SL.",
        "orders": 1,
        "revenue": 99.0
      },
      {
        "account": "Blanca Bergaz",
        "orders": 1,
        "revenue": 75.6
      },
      {
        "account": "Iván Redruello",
        "orders": 1,
        "revenue": 75.6
      },
      {
        "account": "JAIME MASMIQUEL",
        "orders": 1,
        "revenue": 67.93
      },
      {
        "account": "Violeta Cuerda",
        "orders": 1,
        "revenue": 67.93
      },
      {
        "account": "Jordi Font Comas",
        "orders": 1,
        "revenue": 67.93
      },
      {
        "account": "Julio García de Tejada",
        "orders": 1,
        "revenue": 67.93
      },
      {
        "account": "Adolfo Pellicer",
        "orders": 1,
        "revenue": 67.93
      },
      {
        "account": "Erica Chiari",
        "orders": 1,
        "revenue": 67.93
      },
      {
        "account": "Pablo Peña Pérez",
        "orders": 1,
        "revenue": 67.93
      },
      {
        "account": "Pablo Moreno Montes",
        "orders": 1,
        "revenue": 67.93
      },
      {
        "account": "Victor Migoya",
        "orders": 1,
        "revenue": 67.93
      },
      {
        "account": "Paco Diaz Torres",
        "orders": 1,
        "revenue": 67.93
      },
      {
        "account": "Triana Quintana",
        "orders": 1,
        "revenue": 67.93
      },
      {
        "account": "Patricia González Río",
        "orders": 1,
        "revenue": 67.93
      },
      {
        "account": "Sandra Fernandez Fernandez",
        "orders": 1,
        "revenue": 67.93
      },
      {
        "account": "Pernille Louise Foss",
        "orders": 1,
        "revenue": 67.93
      },
      {
        "account": "JUAN MANUEL VARELA PORTELA",
        "orders": 1,
        "revenue": 67.93
      },
      {
        "account": "Juan Cabrero Verge",
        "orders": 1,
        "revenue": 67.93
      },
      {
        "account": "Joaquin Huesca",
        "orders": 1,
        "revenue": 67.93
      },
      {
        "account": "Maribel Muñoz López",
        "orders": 1,
        "revenue": 67.93
      },
      {
        "account": "Juan Jose Estrada Bernal",
        "orders": 1,
        "revenue": 67.93
      },
      {
        "account": "Francisco Ruben Chaves Diaz",
        "orders": 1,
        "revenue": 67.93
      },
      {
        "account": "Juan Pedro Taverna Checa",
        "orders": 1,
        "revenue": 67.93
      },
      {
        "account": "JOSE Sierra",
        "orders": 1,
        "revenue": 67.93
      },
      {
        "account": "Anna Diaz Orpinell",
        "orders": 1,
        "revenue": 67.93
      },
      {
        "account": "Alonso Bermejo Domínguez",
        "orders": 1,
        "revenue": 61.14
      },
      {
        "account": "FERRAN ESCABIA",
        "orders": 1,
        "revenue": 56.7
      },
      {
        "account": "Pedro Mateos",
        "orders": 1,
        "revenue": 56.7
      },
      {
        "account": "DAVID SIERRA DIAZ",
        "orders": 1,
        "revenue": 37.8
      },
      {
        "account": "Belén Martínez",
        "orders": 1,
        "revenue": 37.8
      },
      {
        "account": "Jose Giménez Domenech",
        "orders": 1,
        "revenue": 37.8
      },
      {
        "account": "Belén Gómez Bueno",
        "orders": 1,
        "revenue": 37.8
      },
      {
        "account": "Rebeca Saez",
        "orders": 1,
        "revenue": 37.8
      },
      {
        "account": "ANA MIÑANA",
        "orders": 1,
        "revenue": 37.8
      },
      {
        "account": "Francisco Romera",
        "orders": 1,
        "revenue": 37.8
      },
      {
        "account": "David A. Urgel",
        "orders": 1,
        "revenue": 37.8
      },
      {
        "account": "Trilux José Ángel Vela del Cerro",
        "orders": 1,
        "revenue": 37.8
      },
      {
        "account": "Ramon Dios",
        "orders": 1,
        "revenue": 37.8
      },
      {
        "account": "sol fernandez llanos",
        "orders": 1,
        "revenue": 37.8
      },
      {
        "account": "Amaia Corta",
        "orders": 1,
        "revenue": 37.8
      },
      {
        "account": "Francisco Javier Amador Garrido",
        "orders": 1,
        "revenue": 37.8
      },
      {
        "account": "Juan Páramo Sanz",
        "orders": 1,
        "revenue": 37.8
      },
      {
        "account": "Cristina Gómez Martínez",
        "orders": 1,
        "revenue": 37.8
      },
      {
        "account": "Alberto Araque",
        "orders": 1,
        "revenue": 37.8
      },
      {
        "account": "gala escamilla",
        "orders": 1,
        "revenue": 37.8
      },
      {
        "account": "Naira Quintana",
        "orders": 1,
        "revenue": 37.8
      },
      {
        "account": "Manuel Aracil",
        "orders": 1,
        "revenue": 37.8
      },
      {
        "account": "cristina fernandez",
        "orders": 1,
        "revenue": 37.8
      },
      {
        "account": "Javier Navarro Cano",
        "orders": 1,
        "revenue": 37.8
      },
      {
        "account": "Cristina Cuellar",
        "orders": 1,
        "revenue": 37.8
      },
      {
        "account": "Pilar Carrera",
        "orders": 1,
        "revenue": 37.8
      },
      {
        "account": "Amparo Lorca",
        "orders": 1,
        "revenue": 37.8
      },
      {
        "account": "Enrique Peñas Sanchez",
        "orders": 1,
        "revenue": 34.02
      },
      {
        "account": "Ruben Tena Cardeña",
        "orders": 1,
        "revenue": 28.35
      },
      {
        "account": "Milagros Blanco",
        "orders": 1,
        "revenue": 28.35
      },
      {
        "account": "YOLANDA MOLINA MORENO",
        "orders": 1,
        "revenue": 28.35
      },
      {
        "account": "Jose Manuel Chover Cañamas",
        "orders": 1,
        "revenue": 28.35
      },
      {
        "account": "Aitor GONZALEZ MARTIN",
        "orders": 1,
        "revenue": 28.35
      },
      {
        "account": ". .",
        "orders": 1,
        "revenue": 28.35
      },
      {
        "account": "Domingo ROIG",
        "orders": 1,
        "revenue": 28.35
      },
      {
        "account": "Susana Nieto",
        "orders": 1,
        "revenue": 28.35
      },
      {
        "account": "Cristina Escobar Garcia",
        "orders": 1,
        "revenue": 28.35
      },
      {
        "account": "Aitzol Altuna Gabilondo",
        "orders": 1,
        "revenue": 28.35
      },
      {
        "account": "Ana Rohr",
        "orders": 1,
        "revenue": 28.35
      },
      {
        "account": "MATIAS CUBAS VEGA",
        "orders": 1,
        "revenue": 28.35
      },
      {
        "account": "Lucia Paramio Espinosa",
        "orders": 1,
        "revenue": 28.35
      },
      {
        "account": "MIGUEL GILABERT",
        "orders": 1,
        "revenue": 28.35
      },
      {
        "account": "Jose Sierra luna",
        "orders": 1,
        "revenue": 28.35
      },
      {
        "account": "Juan Maria Hernandez Lopez",
        "orders": 1,
        "revenue": 28.35
      },
      {
        "account": "Pilar Tena",
        "orders": 1,
        "revenue": 28.35
      },
      {
        "account": "Teresa pereyra",
        "orders": 1,
        "revenue": 28.35
      },
      {
        "account": "Angel Virgili",
        "orders": 1,
        "revenue": 28.35
      },
      {
        "account": "Noemi Galiano Fernandez",
        "orders": 1,
        "revenue": 28.35
      },
      {
        "account": "Alexis Llerena Roncero",
        "orders": 1,
        "revenue": 28.35
      },
      {
        "account": "Jose Ramón González",
        "orders": 1,
        "revenue": 28.35
      },
      {
        "account": "Emilio Joaquín Ramos Martínez",
        "orders": 1,
        "revenue": 28.35
      },
      {
        "account": "SUSANA SEGUI DOMINGUEZ",
        "orders": 1,
        "revenue": 28.35
      },
      {
        "account": "Marcos De miguel torresano",
        "orders": 1,
        "revenue": 28.35
      },
      {
        "account": "Sylvia Serrat",
        "orders": 1,
        "revenue": 28.35
      },
      {
        "account": "David Sempere lucas",
        "orders": 1,
        "revenue": 28.35
      },
      {
        "account": "Sílvia Bustos",
        "orders": 1,
        "revenue": 28.35
      },
      {
        "account": "Blanca Cobo",
        "orders": 1,
        "revenue": 28.35
      },
      {
        "account": "Iker Bermudez Valencia",
        "orders": 1,
        "revenue": 28.35
      },
      {
        "account": "Javi Hualde Artola",
        "orders": 1,
        "revenue": 28.35
      },
      {
        "account": "eugenia dura muñoz",
        "orders": 1,
        "revenue": 28.35
      },
      {
        "account": "Francisco González León",
        "orders": 1,
        "revenue": 0.0
      },
      {
        "account": "Marisa Caniego García-Baquero",
        "orders": 1,
        "revenue": 0.0
      }
    ]
  },
  "affiliates": {
    "totals": {
      "orders": 0,
      "revenue": 0.0,
      "commission": 0.0,
      "active_affiliates": 0,
      "total_affiliates": 32,
      "new_affiliates": 0,
      "aov": 0.0,
      "commission_rate": 0.0
    },
    "daily": [
      {
        "date": "2026-06-01",
        "orders": 0,
        "revenue": 0.0,
        "commission": 0.0
      },
      {
        "date": "2026-06-02",
        "orders": 0,
        "revenue": 0.0,
        "commission": 0.0
      },
      {
        "date": "2026-06-03",
        "orders": 0,
        "revenue": 0.0,
        "commission": 0.0
      }
    ],
    "top_affiliates": []
  }
}